korean/__init__.py
korean/__main__.py
korean/data.json
korean/hangul.py
korean/ext/__init__.py
korean/ext/gettext.py
korean/ext/jinja2.py
korean/ext/django/__init__.py
korean/ext/django/apps.py
korean/ext/django/templatetags/__init__.py
korean/ext/django/templatetags/korean.py
korean/l10n/__init__.py
korean/l10n/jinja2ext.py
korean/morphology/__init__.py
korean/morphology/morpheme.py
korean/morphology/particle.py
korean/morphology/substantive.py
korean-0.1.9.dist-info/LICENSE
korean-0.1.9.dist-info/METADATA
korean-0.1.9.dist-info/WHEEL
korean-0.1.9.dist-info/top_level.txt
korean-0.1.9.dist-info/RECORD
